oneliner/__init__.py
oneliner/__main__.py
oneliner/config.py
oneliner/convert.py
oneliner/expr_transform.py
oneliner/expr_unparse.py
oneliner/namespaces.py
oneliner/pending_nodes.py
oneliner/reserved_identifiers.py
oneliner/utils.py
oneliner/version.py
oneliner/presets/__init__.py
oneliner/presets/iter_wrapper.py
oneliner_py-1.2.2.dist-info/licenses/LICENSE
oneliner_py-1.2.2.dist-info/METADATA
oneliner_py-1.2.2.dist-info/WHEEL
oneliner_py-1.2.2.dist-info/top_level.txt
oneliner_py-1.2.2.dist-info/RECORD
