Metadata-Version: 2.4
Name: Oneliner-Py
Version: 1.2.2
Summary: Convert python scripts into oneliner expression.
Author: Yunline
Project-URL: Homepage, https://github.com/yunline/Oneliner-Py
Project-URL: Bug Tracker, https://github.com/yunline/Oneliner-Py/issues
Classifier: Programming Language :: Python :: 3.10
Classifier: Programming Language :: Python :: 3.11
Classifier: Programming Language :: Python :: 3.12
Classifier: Programming Language :: Python :: 3.13
Classifier: Programming Language :: Python :: 3.14
Classifier: Programming Language :: Python :: Implementation :: CPython
Classifier: License :: OSI Approved :: MIT License
Requires-Python: >=3.10
License-File: LICENSE
Dynamic: license-file
